mdproptools/__init__.py
mdproptools/common/__init__.py
mdproptools/common/com_mols.py
mdproptools/common/constants.py
mdproptools/dynamical/__init__.py
mdproptools/dynamical/_conductivity.py
mdproptools/dynamical/conductivity.py
mdproptools/dynamical/diffusion.py
mdproptools/dynamical/residence_time.py
mdproptools/dynamical/viscosity.py
mdproptools/structural/__init__.py
mdproptools/structural/cluster_analysis.py
mdproptools/structural/hydration_number.py
mdproptools/structural/number_density.py
mdproptools/structural/rdf_cn.py
mdproptools/utilities/__init__.py
mdproptools/utilities/fluctuations.py
mdproptools/utilities/log.py
mdproptools/utilities/plots.py
tests/__init__.py
tests/dynamical/__init__.py
tests/dynamical/test_diffusion.py
tests/structural/__init__.py
tests/structural/test_cluster_analysis.py
mdproptools-0.0.6.dist-info/LICENSE
mdproptools-0.0.6.dist-info/METADATA
mdproptools-0.0.6.dist-info/WHEEL
mdproptools-0.0.6.dist-info/top_level.txt
mdproptools-0.0.6.dist-info/RECORD
