Metadata-Version: 2.1
Name: mdproptools
Version: 0.0.6
Summary: mdproptools contains MD analysis tools
Author-email: Rasha Atwi <rasha.atwi@stonybrook.edu>, Matthew Bliss <matthew.bliss@stonybrook.edu>, Maxim Makeev <maxim.makeev@stonybrook.edu>
License: MIT
Project-URL: repository, https://github.com/molmd/mdproptools
Project-URL: changelog, https://github.com/molmd/mdproptools/blob/master/CHANGELOG.md
Keywords: MD,analysis,lammps
Classifier: Programming Language :: Python :: 3
Classifier: Programming Language :: Python :: 3.10
Classifier: Programming Language :: Python :: 3.11
Classifier: Programming Language :: Python :: 3.12
Classifier: Development Status :: 3 - Alpha
Classifier: Intended Audience :: Science/Research
Classifier: Intended Audience :: Information Technology
Classifier: Operating System :: OS Independent
Classifier: Topic :: Scientific/Engineering
Requires-Python: >=3.10
License-File: LICENSE
Requires-Dist: numpy >=1.21.1
Requires-Dist: matplotlib >=3.3.1
Requires-Dist: scipy >=1.6.0
Requires-Dist: pandas >=1.1.2
Requires-Dist: seaborn >=0.11.0
Requires-Dist: statsmodels >=0.12.0
Requires-Dist: numba ==0.56.4
Requires-Dist: llvmlite ==0.39.1
Requires-Dist: tqdm >=4.50.0
Provides-Extra: dev
Requires-Dist: black >=23.3.0 ; extra == 'dev'
Requires-Dist: isort >=5.10.0 ; extra == 'dev'
Requires-Dist: pytest >=7.4.0 ; extra == 'dev'
Requires-Dist: pytest-cov >=3.0.0 ; extra == 'dev'
Requires-Dist: pytest-benchmark >=4.0.0 ; extra == 'dev'
